MANIFEST.in
WALinuxAgent-2.2.14.1.6-1.noarch.rpm
csr_waagent_install.sh
setup.py
csr_azure_agent.egg-info/PKG-INFO
csr_azure_agent.egg-info/SOURCES.txt
csr_azure_agent.egg-info/dependency_links.txt
csr_azure_agent.egg-info/top_level.txt
waagent/Changelog
waagent/LICENSE.txt
waagent/MAINTENANCE.md
waagent/MANIFEST
waagent/MANIFEST.in
waagent/NOTICE
waagent/README.md
waagent/__main__.py
waagent/makepkg.py
waagent/setup.py
waagent/azurelinuxagent/__init__.py
waagent/azurelinuxagent/agent.py
waagent/azurelinuxagent/common/__init__.py
waagent/azurelinuxagent/common/conf.py
waagent/azurelinuxagent/common/dhcp.py
waagent/azurelinuxagent/common/event.py
waagent/azurelinuxagent/common/exception.py
waagent/azurelinuxagent/common/future.py
waagent/azurelinuxagent/common/logger.py
waagent/azurelinuxagent/common/rdma.py
waagent/azurelinuxagent/common/version.py
waagent/azurelinuxagent/common/osutil/__init__.py
waagent/azurelinuxagent/common/osutil/alpine.py
waagent/azurelinuxagent/common/osutil/arch.py
waagent/azurelinuxagent/common/osutil/bigip.py
waagent/azurelinuxagent/common/osutil/clearlinux.py
waagent/azurelinuxagent/common/osutil/coreos.py
waagent/azurelinuxagent/common/osutil/debian.py
waagent/azurelinuxagent/common/osutil/default.py
waagent/azurelinuxagent/common/osutil/factory.py
waagent/azurelinuxagent/common/osutil/freebsd.py
waagent/azurelinuxagent/common/osutil/gaia.py
waagent/azurelinuxagent/common/osutil/openbsd.py
waagent/azurelinuxagent/common/osutil/redhat.py
waagent/azurelinuxagent/common/osutil/suse.py
waagent/azurelinuxagent/common/osutil/ubuntu.py
waagent/azurelinuxagent/common/protocol/__init__.py
waagent/azurelinuxagent/common/protocol/hostplugin.py
waagent/azurelinuxagent/common/protocol/metadata.py
waagent/azurelinuxagent/common/protocol/ovfenv.py
waagent/azurelinuxagent/common/protocol/restapi.py
waagent/azurelinuxagent/common/protocol/util.py
waagent/azurelinuxagent/common/protocol/wire.py
waagent/azurelinuxagent/common/utils/__init__.py
waagent/azurelinuxagent/common/utils/cryptutil.py
waagent/azurelinuxagent/common/utils/fileutil.py
waagent/azurelinuxagent/common/utils/flexible_version.py
