Metadata-Version: 1.1
Name: csr-azure-agent
Version: 0.0.5
Summary: A library to install Azure Waagent on CSR
Home-page: https://github4-chn.cisco.com/csr1000v-azure/csr_azure_agent
Author: Christopher Reder
Author-email: creder@cisco.com
License: MIT
Download-URL: https://github4-chn.cisco.com/csr1000v-azure/csr_azure_agent/archive/0.0.5.tar.gz
Keywords: cisco,azure,csr1000v,csr,guestshell
Platform: UNKNOWN
